<annotation>
	<folder>collectedimages</folder>
	<filename>C.fe767f0a-c787-11ec-b505-f09e4a8b5adc.jpg</filename>
	<path>C:\Users\fujef\RealTimeObjectDetection\Tensorflow\workspace\images\collectedimages\C.fe767f0a-c787-11ec-b505-f09e4a8b5adc.jpg</path>
	<source>
		<database>Unknown</database>
	</source>
	<size>
		<width>640</width>
		<height>480</height>
		<depth>3</depth>
	</size>
	<segmented>0</segmented>
	<object>
		<name>C</name>
		<pose>Unspecified</pose>
		<truncated>0</truncated>
		<difficult>0</difficult>
		<bndbox>
			<xmin>251</xmin>
			<ymin>187</ymin>
			<xmax>428</xmax>
			<ymax>351</ymax>
		</bndbox>
	</object>
</annotation>
